{
  "Origins": "",
  "Fact Check": "",
  "Description": "",
  "Originally Published": " 29 January 2016",
  "Referred Links": "http://www.mstarz.com/articles/103367/20160127/bill-murray-running-president-2016-election-ghostbusters-star.htm;",
  "Example": "",
  "Last Updated": "29 January 2016",
  "Credibility": "false",
  "URL": "www.snopes.com/bill-murray-run-president/",
  "Claim": "Comedian Bill Murray is running for president.",
  "Tags": "fake news;president;bill murray;",
  "Claim_ID": "bill-murray-run-president"
}