{
  "Origins": "This legend is an older version of the pull tab story, one about collecting large quantities of various worthless items to exchange for seeing eye dogs. As a 1948 book said of this rumor:",
  "Fact Check": "",
  "Description": "Barbara \"seeing eye to eye with an old rumor\" Mikkelson",
  "Originally Published": "",
  "Referred Links": "",
  "Example": "",
  "Last Updated": "24 May 2011",
  "Credibility": "false",
  "URL": "www.snopes.com/business/redeem/cigarettes.asp",
  "Claim": "Cigarette packs were once redeemable to help the blind defray the cost of purchasing seeing-eye dogs.",
  "Claim_ID": "business_redeem_cigarettes",
  "Tags": ""
}