{
  "Origins": "",
  "Fact Check": "",
  "Description": "",
  "Originally Published": "",
  "Referred Links": "http://www.indystar.com/apps/pbcs.dll/article?AID=/20050831/BUSINESS/508310389;http://quote.bloomberg.com/apps/news?pid=10000006&sid=aHqhEmdWCp4U;http://www.forbes.com/work/feeds/ap/2005/08/31/ap2200112.html;http://money.cnn.com/2005/08/31/news/gas_prices/;http://quote.bloomberg.com/apps/news?pid=10000103&sid=aFyUsDZlNR9o;http://www.wtok.com/news/headlines/1710826.html;http://www.11alive.com/news/news_article.aspx?storyid=68623;http://www.wmcstations.com/Global/story.asp?S=3795496;http://www.ardemgaz.com/ShowStoryTemplate.asp?Path=ArDemocrat/2005/08/31&ID=Ar00900&Section=National;http://www.allheadlinenews.com/articles/2250908522;http://www.mercurynews.com/mld/mercurynews/news/politics/12516266.htm;http://www.orlandosentinel.com/sports/highschool/orl-bk-blockerrelease083105,0,5214401.story;http://www.local10.com/news/4918480/detail.html;",
  "Example": "",
  "Last Updated": "",
  "Credibility": "true",
  "URL": "www.snopes.com/politics/gasoline/katrina.asp",
  "Claim": "Various rumors about the effect of Hurricane Katrina on gasoline supplies and prices.",
  "Claim_ID": "politics_gasoline_katrina",
  "Tags": ""
}